AUTHORS
LICENSE
MANIFEST.in
NEWS
README.md
argparse-manpage
pyproject.toml
setup.cfg
setup.py
argparse_manpage/__init__.py
argparse_manpage/cli.py
argparse_manpage/compat.py
argparse_manpage/manpage.py
argparse_manpage/tooling.py
argparse_manpage.egg-info/PKG-INFO
argparse_manpage.egg-info/SOURCES.txt
argparse_manpage.egg-info/dependency_links.txt
argparse_manpage.egg-info/entry_points.txt
argparse_manpage.egg-info/requires.txt
argparse_manpage.egg-info/top_level.txt
build_manpages/__init__.py
build_manpages/build_manpage.py
build_manpages/build_manpages.py
build_manpages/compat.py
build_manpages/manpage.py
examples/argument_groups/setup.cfg
examples/argument_groups/setup.py
examples/argument_groups/bin/test
examples/argument_groups/expected/test.1
examples/copr/expected-output.1
examples/copr/expected-output.1.python3.13
examples/copr/setup.cfg
examples/copr/setup.py
examples/copr/copr_cli/__init__.py
examples/copr/copr_cli/build_config.py
examples/copr/copr_cli/main.py
examples/copr/copr_cli/util.py
examples/copr/fake-deps/HACK
examples/copr/fake-deps/jinja2.py
examples/copr/fake-deps/simplejson.py
examples/copr/fake-deps/copr/README
examples/copr/fake-deps/copr/__init__.py
examples/copr/fake-deps/copr/exceptions.py
examples/copr/fake-deps/copr/client/__init__.py
examples/copr/fake-deps/copr/client/responses.py
examples/old_format/README.md
examples/old_format/example.py
examples/old_format/expected-output.1
examples/old_format/setup.cfg
examples/old_format/setup.py
examples/old_format_file_name/README.md
examples/old_format_file_name/example.py
examples/old_format_file_name/expected-output.1
examples/old_format_file_name/setup.cfg
examples/old_format_file_name/setup.py
examples/osc/expected-output.1
examples/osc/setup.cfg
examples/osc/setup.py
examples/osc/osc/__init__.py
examples/osc/osc/main.py
examples/pre-written-man-page/psutils.1
examples/pre-written-man-page/setup.cfg
examples/pre-written-man-page/setup.py
examples/raw-description/expected-output.1
examples/raw-description/setup.cfg
examples/raw-description/setup.py
examples/raw-description/bin/dg
examples/resalloc/requirements.txt
examples/resalloc/setup.cfg
examples/resalloc/setup.py
examples/resalloc/bin/resalloc
