Metadata-Version: 2.4
Name: argparse-manpage
Version: 4.7
Summary: Build manual page from python's ArgumentParser object.
Home-page: https://github.com/praiskup/argparse-manpage
Author: Gabriele Giammatteo
Author-email: gabriele.giammatteo@eng.it
Maintainer: Pavel Raiskup
Maintainer-email: praiskup@redhat.com
License: Apache-2.0
License-File: LICENSE
License-File: AUTHORS
Requires-Dist: tomli; python_version < "3.11"
Provides-Extra: setuptools
Requires-Dist: setuptools; extra == "setuptools"
Dynamic: author
Dynamic: author-email
Dynamic: description
Dynamic: description-content-type
Dynamic: home-page
Dynamic: license
Dynamic: license-file
Dynamic: maintainer
Dynamic: maintainer-email
Dynamic: provides-extra
Dynamic: requires-dist
Dynamic: summary
